{"gF":{"$":0,"a":{"fu":{"$":0,"a":1522261421},"bO":{"$":0},"fS":{"$":0},"e1":{"bq":{"$":-1,"a":1,"b":{"a":{"$":"$L","a":["Browser","Events"]},"b":"Hidden"},"c":0,"d":{"$":-1,"a":1,"b":{"a":{"$":"$L","a":["Basics"]},"b":"True"},"c":0,"d":{"$":-1,"a":1,"b":{"a":{"$":"$L","a":["Basics"]},"b":"False"},"c":0,"d":{"$":-1,"a":1,"b":{"a":{"$":"$L","a":["Basics"]},"b":"EQ"},"c":0,"d":{"$":-2},"e":{"$":-2}},"e":{"$":-1,"a":1,"b":{"a":{"$":"$L","a":["Basics"]},"b":"LT"},"c":0,"d":{"$":-1,"a":0,"b":{"a":{"$":"$L","a":["Basics"]},"b":"GT"},"c":0,"d":{"$":-2},"e":{"$":-2}},"e":{"$":-2}}},"e":{"$":-1,"a":1,"b":{"a":{"$":"$L","a":["Browser"]},"b":"Internal"},"c":0,"d":{"$":-1,"a":1,"b":{"a":{"$":"$L","a":["Browser"]},"b":"External"},"c":0,"d":{"$":-2},"e":{"$":-2}},"e":{"$":-1,"a":1,"b":{"a":{"$":"$L","a":["Browser","Dom"]},"b":"NotFound"},"c":0,"d":{"$":-2},"e":{"$":-2}}}},"e":{"$":-1,"a":1,"b":{"a":{"$":"$L","a":["Maybe"]},"b":"Just"},"c":0,"d":{"$":-1,"a":1,"b":{"a":{"$":"$L","a":["List","Extra"]},"b":"Continue"},"c":0,"d":{"$":-1,"a":0,"b":{"a":{"$":"$L","a":["Json","Decode"]},"b":"Field"},"c":0,"d":{"$":-1,"a":1,"b":{"a":{"$":"$L","a":["Json","Decode"]},"b":"Failure"},"c":0,"d":{"$":-1,"a":0,"b":{"a":{"$":"$L","a":["Browser","Events"]},"b":"Visible"},"c":0,"d":{"$":-2},"e":{"$":-2}},"e":{"$":-2}},"e":{"$":-1,"a":1,"b":{"a":{"$":"$L","a":["Json","Decode"]},"b":"OneOf"},"c":0,"d":{"$":-1,"a":0,"b":{"a":{"$":"$L","a":["Json","Decode"]},"b":"Index"},"c":0,"d":{"$":-2},"e":{"$":-2}},"e":{"$":-2}}},"e":{"$":-1,"a":1,"b":{"a":{"$":"$L","a":["List","Extra"]},"b":"Stop"},"c":0,"d":{"$":-2},"e":{"$":-2}}},"e":{"$":-1,"a":1,"b":{"a":{"$":"$L","a":["Result"]},"b":"Err"},"c":0,"d":{"$":-1,"a":1,"b":{"a":{"$":"$L","a":["Maybe"]},"b":"Nothing"},"c":0,"d":{"$":-2},"e":{"$":-2}},"e":{"$":-1,"a":1,"b":{"a":{"$":"$L","a":["Result"]},"b":"Ok"},"c":0,"d":{"$":-2},"e":{"$":-2}}}}},"ap":{"$":-1,"a":1,"b":{"$":"$L","a":["Random","Date"]},"c":{"$":-2},"d":{"$":-1,"a":0,"b":{"$":"$L","a":["List"]},"c":{"$":-2},"d":{"$":-1,"a":1,"b":{"$":"$L","a":["Html"]},"c":{"$":-2},"d":{"$":-1,"a":0,"b":{"$":"$L","a":["Browser","Navigation"]},"c":{"$":-2},"d":{"$":-1,"a":1,"b":{"$":"$L","a":["Browser","Dom"]},"c":{"$":-1,"a":1,"b":"NotFound","c":0,"d":{"$":-2},"e":{"$":-2}},"d":{"$":-1,"a":0,"b":{"$":"$L","a":["Basics"]},"c":{"$":-1,"a":1,"b":"LT","c":0,"d":{"$":-1,"a":0,"b":"False","c":0,"d":{"$":-1,"a":1,"b":"EQ","c":0,"d":{"$":-2},"e":{"$":-2}},"e":{"$":-1,"a":1,"b":"GT","c":0,"d":{"$":-2},"e":{"$":-2}}},"e":{"$":-1,"a":1,"b":"True","c":0,"d":{"$":-2},"e":{"$":-2}}},"d":{"$":-1,"a":1,"b":{"$":"$L","a":["Array"]},"c":{"$":-2},"d":{"$":-2},"e":{"$":-2}},"e":{"$":-1,"a":1,"b":{"$":"$L","a":["Browser"]},"c":{"$":-1,"a":1,"b":"Internal","c":0,"d":{"$":-1,"a":0,"b":"External","c":0,"d":{"$":-2},"e":{"$":-2}},"e":{"$":-2}},"d":{"$":-1,"a":0,"b":{"$":"$L","a":["Bitwise"]},"c":{"$":-2},"d":{"$":-2},"e":{"$":-2}},"e":{"$":-2}}},"e":{"$":-1,"a":1,"b":{"$":"$L","a":["Browser","Events"]},"c":{"$":-1,"a":1,"b":"Visible","c":0,"d":{"$":-1,"a":0,"b":"Hidden","c":0,"d":{"$":-2},"e":{"$":-2}},"e":{"$":-2}},"d":{"$":-2},"e":{"$":-2}}},"e":{"$":-1,"a":1,"b":{"$":"$L","a":["Debug"]},"c":{"$":-2},"d":{"$":-1,"a":1,"b":{"$":"$L","a":["Char"]},"c":{"$":-2},"d":{"$":-2},"e":{"$":-2}},"e":{"$":-1,"a":1,"b":{"$":"$L","a":["Dict"]},"c":{"$":-2},"d":{"$":-2},"e":{"$":-2}}}},"e":{"$":-1,"a":1,"b":{"$":"$L","a":["Html","Lazy"]},"c":{"$":-2},"d":{"$":-1,"a":0,"b":{"$":"$L","a":["Html","Events"]},"c":{"$":-2},"d":{"$":-1,"a":1,"b":{"$":"$L","a":["Html","Attributes"]},"c":{"$":-2},"d":{"$":-2},"e":{"$":-2}},"e":{"$":-1,"a":1,"b":{"$":"$L","a":["Html","Keyed"]},"c":{"$":-2},"d":{"$":-2},"e":{"$":-2}}},"e":{"$":-1,"a":1,"b":{"$":"$L","a":["Json","Encode"]},"c":{"$":-2},"d":{"$":-1,"a":0,"b":{"$":"$L","a":["Json","Decode"]},"c":{"$":-1,"a":1,"b":"Index","c":0,"d":{"$":-1,"a":1,"b":"Field","c":0,"d":{"$":-1,"a":0,"b":"Failure","c":0,"d":{"$":-2},"e":{"$":-2}},"e":{"$":-2}},"e":{"$":-1,"a":1,"b":"OneOf","c":0,"d":{"$":-2},"e":{"$":-2}}},"d":{"$":-2},"e":{"$":-2}},"e":{"$":-2}}}},"e":{"$":-1,"a":1,"b":{"$":"$L","a":["Platform","Cmd"]},"c":{"$":-2},"d":{"$":-1,"a":1,"b":{"$":"$L","a":["Maybe"]},"c":{"$":-1,"a":1,"b":"Nothing","c":0,"d":{"$":-1,"a":0,"b":"Just","c":0,"d":{"$":-2},"e":{"$":-2}},"e":{"$":-2}},"d":{"$":-1,"a":1,"b":{"$":"$L","a":["List","Extra"]},"c":{"$":-1,"a":1,"b":"Stop","c":0,"d":{"$":-1,"a":0,"b":"Continue","c":0,"d":{"$":-2},"e":{"$":-2}},"e":{"$":-2}},"d":{"$":-2},"e":{"$":-2}},"e":{"$":-1,"a":1,"b":{"$":"$L","a":["Platform"]},"c":{"$":-2},"d":{"$":-2},"e":{"$":-2}}},"e":{"$":-1,"a":1,"b":{"$":"$L","a":["Random","Array"]},"c":{"$":-2},"d":{"$":-1,"a":1,"b":{"$":"$L","a":["Process"]},"c":{"$":-2},"d":{"$":-1,"a":0,"b":{"$":"$L","a":["Platform","Sub"]},"c":{"$":-2},"d":{"$":-2},"e":{"$":-2}},"e":{"$":-2}},"e":{"$":-1,"a":1,"b":{"$":"$L","a":["Random","Char"]},"c":{"$":-2},"d":{"$":-2},"e":{"$":-2}}}}},"e":{"$":-1,"a":1,"b":{"$":"$L","a":["Random","String"]},"c":{"$":-2},"d":{"$":-1,"a":0,"b":{"$":"$L","a":["Random","Int"]},"c":{"$":-2},"d":{"$":-1,"a":1,"b":{"$":"$L","a":["Random","Extra"]},"c":{"$":-2},"d":{"$":-1,"a":1,"b":{"$":"$L","a":["Random","Dict"]},"c":{"$":-2},"d":{"$":-2},"e":{"$":-2}},"e":{"$":-1,"a":1,"b":{"$":"$L","a":["Random","Float"]},"c":{"$":-2},"d":{"$":-2},"e":{"$":-2}}},"e":{"$":-1,"a":1,"b":{"$":"$L","a":["Random","Order"]},"c":{"$":-2},"d":{"$":-1,"a":1,"b":{"$":"$L","a":["Random","List"]},"c":{"$":-2},"d":{"$":-2},"e":{"$":-2}},"e":{"$":-1,"a":1,"b":{"$":"$L","a":["Random","Set"]},"c":{"$":-2},"d":{"$":-2},"e":{"$":-2}}}},"e":{"$":-1,"a":1,"b":{"$":"$L","a":["Task"]},"c":{"$":-2},"d":{"$":-1,"a":0,"b":{"$":"$L","a":["Set"]},"c":{"$":-2},"d":{"$":-1,"a":1,"b":{"$":"$L","a":["Result"]},"c":{"$":-1,"a":1,"b":"Ok","c":0,"d":{"$":-1,"a":0,"b":"Err","c":0,"d":{"$":-2},"e":{"$":-2}},"e":{"$":-2}},"d":{"$":-2},"e":{"$":-2}},"e":{"$":-1,"a":1,"b":{"$":"$L","a":["String"]},"c":{"$":-2},"d":{"$":-2},"e":{"$":-2}}},"e":{"$":-1,"a":1,"b":{"$":"$L","a":["Tuple"]},"c":{"$":-2},"d":{"$":-2},"e":{"$":-2}}}}}},"hs":2484997123}},"es":{"$":1},"gT":{"$":1},"cg":{"$":1},"aj":{"$":-1,"a":1,"b":"src/Leafy.elm","c":{"fu":2202873449,"bO":{"$":0},"eL":{"$":"$L","a":[2484997123]},"eN":false,"e1":{"bq":{"$":-2},"ap":{"$":-1,"a":1,"b":{"$":"$L","a":["Leafy"]},"c":{"$":-1,"a":1,"b":"Up","c":0,"d":{"$":-1,"a":0,"b":"Randomize","c":0,"d":{"$":-2},"e":{"$":-2}},"e":{"$":-2}},"d":{"$":-2},"e":{"$":-2}}},"hs":1805003684},"d":{"$":-2},"e":{"$":-2}},"f6":{"$":1}}